PDF/__init__.py
PDF/__main__.py
PDFrewrite-2.2.dist-info/METADATA
PDFrewrite-2.2.dist-info/WHEEL
PDFrewrite-2.2.dist-info/entry_points.txt
PDFrewrite-2.2.dist-info/top_level.txt
PDFrewrite-2.2.dist-info/RECORD
