Metadata-Version: 2.1
Name: PDFrewrite
Version: 2.2
Summary: 可用于移除PDF中空白页，并选择是否保留文字/图像页
Author: ivyZ
Requires-Dist: PyPDF4
